{
  "applications": "*",
  "changelogDate": "20230904002256",
  "dto": "mapstruct",
  "embedded": false,
  "entityTableName": "estado_dissertacao",
  "fields": [
    {
      "fieldName": "codigo",
      "fieldType": "String",
      "fieldValidateRules": ["required", "unique"]
    },
    {
      "fieldName": "nome",
      "fieldType": "String",
      "fieldValidateRules": ["required", "unique"]
    },
    {
      "fieldName": "etapa",
      "fieldType": "Integer",
      "fieldValidateRules": ["min"],
      "fieldValidateRulesMin": "0"
    },
    {
      "fieldName": "descricao",
      "fieldType": "byte[]",
      "fieldTypeBlobContent": "text"
    }
  ],
  "fluentMethods": true,
  "jpaMetamodelFiltering": true,
  "name": "EstadoDissertacao",
  "pagination": "pagination",
  "readOnly": false,
  "relationships": [
    {
      "otherEntityName": "dissertacaoFinalCurso",
      "otherEntityRelationshipName": "estado",
      "relationshipName": "dissertacaoFinalCurso",
      "relationshipType": "one-to-many"
    }
  ],
  "service": "serviceImpl"
}
